{
    "_links": {
        "self": {
            "href": "https:\/\/default\/admin\/structure\/menu\/item\/1\/edit?_format=hal_json"
        },
        "type": {
            "href": "http:\/\/drupal.org\/rest\/type\/menu_link_content\/menu_link_content"
        }
    },
    "uuid": [
        {
            "value": "ed2d59ee-3ce3-4458-a7f9-582df01e1832"
        }
    ],
    "langcode": [
        {
            "value": "en",
            "lang": "en"
        }
    ],
    "bundle": [
        {
            "value": "menu_link_content"
        }
    ],
    "title": [
        {
            "value": "Blog",
            "lang": "en"
        }
    ],
    "menu_name": [
        {
            "value": "main"
        }
    ],
    "link": [
        {
            "uri": "internal:\/blog\/modern",
            "title": "",
            "options": []
        }
    ],
    "external": [
        {
            "value": false
        }
    ],
    "rediscover": [
        {
            "value": true
        }
    ],
    "weight": [
        {
            "value": -49
        }
    ],
    "expanded": [
        {
            "value": false
        }
    ],
    "enabled": [
        {
            "value": true
        }
    ],
    "changed": [
        {
            "value": "2018-01-13T11:33:07+00:00",
            "lang": "en",
            "format": "Y-m-d\\TH:i:sP"
        }
    ],
    "default_langcode": [
        {
            "value": true,
            "lang": "en"
        }
    ]
}